unifi_network_maps/__init__.py
unifi_network_maps/__main__.py
unifi_network_maps/adapters/__init__.py
unifi_network_maps/adapters/config.py
unifi_network_maps/adapters/unifi.py
unifi_network_maps/assets/__init__.py
unifi_network_maps/assets/icons/__init__.py
unifi_network_maps/assets/icons/access-point.svg
unifi_network_maps/assets/icons/laptop.svg
unifi_network_maps/assets/icons/router-network.svg
unifi_network_maps/assets/icons/server-network.svg
unifi_network_maps/assets/icons/server.svg
unifi_network_maps/assets/icons/isometric/ISOPACKS_LICENSE
unifi_network_maps/assets/icons/isometric/block.svg
unifi_network_maps/assets/icons/isometric/cache.svg
unifi_network_maps/assets/icons/isometric/cardterminal.svg
unifi_network_maps/assets/icons/isometric/cloud.svg
unifi_network_maps/assets/icons/isometric/cronjob.svg
unifi_network_maps/assets/icons/isometric/cube.svg
unifi_network_maps/assets/icons/isometric/desktop.svg
unifi_network_maps/assets/icons/isometric/diamond.svg
unifi_network_maps/assets/icons/isometric/dns.svg
unifi_network_maps/assets/icons/isometric/document.svg
unifi_network_maps/assets/icons/isometric/firewall.svg
unifi_network_maps/assets/icons/isometric/function-module.svg
unifi_network_maps/assets/icons/isometric/image.svg
unifi_network_maps/assets/icons/isometric/laptop.svg
unifi_network_maps/assets/icons/isometric/loadbalancer.svg
unifi_network_maps/assets/icons/isometric/lock.svg
unifi_network_maps/assets/icons/isometric/mail.svg
unifi_network_maps/assets/icons/isometric/mailmultiple.svg
unifi_network_maps/assets/icons/isometric/mobiledevice.svg
unifi_network_maps/assets/icons/isometric/office.svg
unifi_network_maps/assets/icons/isometric/package-module.svg
unifi_network_maps/assets/icons/isometric/paymentcard.svg
unifi_network_maps/assets/icons/isometric/plane.svg
unifi_network_maps/assets/icons/isometric/printer.svg
unifi_network_maps/assets/icons/isometric/pyramid.svg
unifi_network_maps/assets/icons/isometric/queue.svg
unifi_network_maps-1.4.15.dist-info/licenses/LICENSE
unifi_network_maps-1.4.15.dist-info/METADATA
unifi_network_maps-1.4.15.dist-info/WHEEL
unifi_network_maps-1.4.15.dist-info/entry_points.txt
unifi_network_maps-1.4.15.dist-info/top_level.txt
unifi_network_maps-1.4.15.dist-info/RECORD
