Metadata-Version: 2.4
Name: unifi-network-maps
Version: 1.4.15
Summary: Dynamic UniFi -> network maps in mermaid or svg
Author: Merlijn
License-Expression: MIT
Project-URL: Homepage, https://github.com/merlijntishauser/unifi-network-maps
Project-URL: Repository, https://github.com/merlijntishauser/unifi-network-maps
Project-URL: Issues, https://github.com/merlijntishauser/unifi-network-maps/issues
Project-URL: Changelog, https://github.com/merlijntishauser/unifi-network-maps/blob/main/CHANGELOG.md
Keywords: unifi,mermaid,network,topology,diagram,svg
Classifier: Development Status :: 3 - Alpha
Classifier: Intended Audience :: System Administrators
Classifier: Operating System :: OS Independent
Classifier: Programming Language :: Python :: 3
Classifier: Programming Language :: Python :: 3 :: Only
Classifier: Programming Language :: Python :: 3.12
Classifier: Programming Language :: Python :: 3.13
Classifier: Topic :: Documentation
Classifier: Topic :: System :: Networking
Requires-Python: >=3.12
License-File: LICENSE
Requires-Dist: unifi-controller-api==0.3.2
Requires-Dist: python-dotenv==1.2.1
Requires-Dist: PyYAML==6.0.3
Requires-Dist: Jinja2==3.1.6
Provides-Extra: dev
Requires-Dist: Faker==40.1.2; extra == "dev"
Requires-Dist: behave==1.3.3; extra == "dev"
Requires-Dist: pre-commit==4.5.1; extra == "dev"
Requires-Dist: pytest==9.0.2; extra == "dev"
Requires-Dist: pytest-cov==7.0.0; extra == "dev"
Requires-Dist: pyright==1.1.408; extra == "dev"
Requires-Dist: ruff==0.14.14; extra == "dev"
Dynamic: license-file
